["def handler(raw: str):\n    if (raw.count('-') != 1): return None\n    s1, _, s2 = raw.partition('-')\n    if (not s1) or (not s2): return None\n    return [s1.upper(), s2.upper()]", "def handler(raw: str):\n    raw = raw.lower()\n    if raw.count(\" \") != 1: return None\n\n    if raw.endswith(\"yd\") or raw.endswith(\"yard\"):\n        return raw.split()[0].upper()\n    return None", "def handler(raw: str):\n    \n    singles = [\n        \"AJJ\"\n    ]\n    if raw in singles:\n        return [raw, raw]\n", "def handler(raw: str):\n    \n    singles = [\n        \"AJJ\", \"MKK\"\n    ]\n    if raw in singles:\n        return [raw, raw]\n", "def handler(raw: str):\n    \n    singles = [\n        \"AJJ\", \"MKK\", \"MLMR\"\n    ]\n    if raw in singles:\n        return [raw, raw]\n", "def handler(raw: str):\n    if raw == \"WJ R YD\": return [\"WJR\", \"WJR\"]\n", "def handler(raw: str):\n    if raw == \"MS\": return [raw, raw]\n", "def handler(raw: str):\n    if raw == \"AB\": return [raw, raw]\n", "def handler(raw: str):\n    if raw == \"TVT\": return [raw, raw]\n", "def handler(raw: str):\n    if raw == \"TVT Y D\": return [\"TVT\", \"TVT\"]\n", "def handler(raw: str):\n    if raw == \"AIPP\": return [raw, raw]\n", "def handler(raw: str):\n    if raw.count(\" \") == 2:\n        if raw.endswith(\"Y D\"):\n            return raw.split()[0].upper()\n\n", "def handler(raw: str):\n    if raw == \"VLK\": return [raw, raw]\n\n", "def handler(raw: str):\n    if raw == \"PYA\": return [raw, raw]\n\n", "def handler(raw: str):\n    if raw == \"JTJ TD\": return [\"JTJ\", \"JTJ\"]\n\n", "def handler(raw: str):\n    if raw == \"PTMS\": return [raw, raw]\n\n", "def handler(raw: str):\n    if raw == \"MPK\": return [raw, raw]\n\n", "def handler(raw: str):\n    if raw == \"TNPM\": return [raw, raw]\n\n", "def handler(raw: str):\n    \n    if raw == \"ENRyard\": return [\"ENR\", \"ENR\"]\n\n", "def handler(raw: str):\n    \n    if raw == \"KBTYD\": return [\"KBT\", \"KBT\"]\n\n", "def handler(raw: str):\n    \n    if raw == \"KPD\": return [raw, raw]\n\n", "def handler(raw: str):\n    \n    if raw == \"MSB\": return [raw, raw]\n\n", "def handler(raw: str):\n    \n    if raw == \"RPM\": return [raw, raw]\n\n", "def handler(raw: str):\n    \n    if raw == \"TBM\": return [raw, raw]\n\n", "def handler(raw: str):\n    \n    if raw == \"TBMYD\": return [\"TBM\", \"TBM\"]\n\n", "def handler(raw: str):\n    \n    if raw == \"PDDYD\": return [\"PDD\", \"PDD\"]\n\n", "def handler(raw: str):\n    \n    if raw == \"KOKYD\": return [\"KOK\", \"KOK\"]\n\n", "def handler(raw: str):\n    \n    if raw == \"MLPM\": return [raw, raw]\n\n"]